pymee/__init__.py
pymee/const.py
pymee/model.py
pymee-2.2.0.dist-info/LICENSE
pymee-2.2.0.dist-info/METADATA
pymee-2.2.0.dist-info/WHEEL
pymee-2.2.0.dist-info/top_level.txt
pymee-2.2.0.dist-info/RECORD
