Metadata-Version: 2.1
Name: pymee
Version: 2.2.0
Summary: a python library to interact with homee
Home-page: https://github.com/FreshlyBrewedCode/pymee
Author: FreshlyBrewedCode
Classifier: Programming Language :: Python :: 3
Classifier: License :: OSI Approved :: MIT License
Classifier: Operating System :: OS Independent
Requires-Python: >=3.6
License-File: LICENSE
